figaro/__init__.py
figaro/_likelihood.py
figaro/_numba_functions.py
figaro/_spin_prior.py
figaro/cosmology.py
figaro/credible_regions.py
figaro/cumulative.py
figaro/decorators.py
figaro/diagnostic.py
figaro/exceptions.py
figaro/load.py
figaro/marginal.py
figaro/mixture.py
figaro/montecarlo.py
figaro/plot.py
figaro/plot_settings.py
figaro/rate.py
figaro/transform.py
figaro/utils.py
figaro/_pipelines/__init__.py
figaro/_pipelines/hierarchical_inference.py
figaro/_pipelines/par_hierarchical_inference.py
figaro/_pipelines/par_probability_density.py
figaro/_pipelines/probability_density.py
figaro-1.10.3.dist-info/licenses/LICENSE
figaro-1.10.3.dist-info/METADATA
figaro-1.10.3.dist-info/WHEEL
figaro-1.10.3.dist-info/entry_points.txt
figaro-1.10.3.dist-info/top_level.txt
figaro-1.10.3.dist-info/RECORD
