Metadata-Version: 2.4
Name: figaro
Version: 1.10.3
Summary: FIGARO: Fast Inference for GW Astronomy, Research & Observations
Author-email: Stefano Rinaldi <stefano.rinaldi@uni-heidelberg.de>, Walter Del Pozzo <walter.delpozzo@unipi.it>
License: MIT License
Project-URL: Documentation, https://figaro.readthedocs.io
Project-URL: Repository, https://github.com/sterinaldi/FIGARO.git
Project-URL: Issues, https://github.com/sterinaldi/FIGARO/issues
Keywords: DPGMM,HDPGMM,figaro,hierarchical,inference
Classifier: Development Status :: 5 - Production/Stable
Classifier: Intended Audience :: Science/Research
Classifier: License :: OSI Approved :: MIT License
Classifier: Programming Language :: Python :: 3
Classifier: Programming Language :: Python :: 3.9
Classifier: Programming Language :: Python :: 3.10
Classifier: Programming Language :: Python :: 3.11
Classifier: Programming Language :: Python :: 3.12
Classifier: Topic :: Scientific/Engineering :: Astronomy
Classifier: Topic :: Scientific/Engineering :: Physics
Requires-Python: >=3.9
License-File: LICENSE
Requires-Dist: numpy>1.22
Requires-Dist: scipy
Requires-Dist: matplotlib!=3.6.3
Requires-Dist: dill
Requires-Dist: corner
Requires-Dist: numba
Requires-Dist: h5py
Requires-Dist: tqdm
Requires-Dist: astropy
Requires-Dist: ray
Dynamic: license-file
